Workbook

Sheet Results
A1: Results
A2: Calculated from Inputs. Hurdle test at the bottom.
A4: Result | B4: Pessimistic | C4: Optimistic
A5: Total cost (36 months) | B5: =SUM(Model!F5:F40) -> 1500000 | C5: =SUM(Model!N5:N40) -> 1500000
A6: Total benefit (36 months) | B6: =SUM(Model!D5:D40)+SUM(Model!E5:E40) -> 2001000 | C6: =SUM(Model!L5:L40)+SUM(Model!M5:M40) -> 4017000
A7: Net present value | B7: =SUM(Model!I5:I40) -> 252678.37 | C7: =SUM(Model!Q5:Q40) -> 1874228.4
A8: Return on investment | B8: =(B6-B5)/B5 -> 0.334 | C8: =(C6-C5)/C5 -> 1.678
A9: Breakeven month | B9: =IF(COUNT(Model!J5:J40)=0,"None in 36 months",MIN(Model!J5:J40)) -> 29 | C9: =IF(COUNT(Model!R5:R40)=0,"None in 36 months",MIN(Model!R5:R40)) -> 19
A10: Annual value at steady state | B10: =Inputs!B5*12*Inputs!B6*Inputs!B9*Inputs!B10+Inputs!B11*Inputs!B12*Inputs!B13 -> 1158000 | C10: =Inputs!C5*12*Inputs!C6*Inputs!C9*Inputs!C10+Inputs!C11*Inputs!C12*Inputs!C13 -> 2157000
A12: Hurdle test
A13: Pessimistic NPV above zero? | B13: =IF(B7>0,"Yes","No") -> Yes
A14: Pessimistic breakeven within hurdle? | B14: =IF(ISNUMBER(B9),IF(B9<=Inputs!B19,"Yes","No"),"No") -> Yes
A15: Clears the hurdle? | B15: =IF(AND(B13="Yes",B14="Yes"),"GO: clears the hurdle","FIX or STOP: does not clear") -> GO: clears the hurdle

Sheet Inputs
A1: 3. Business case model
A2: Use in Prioritize. Fill in the amber cells; Model and Results update. Figures are the fictional retail example.
A4: Input | B4: Pessimistic | C4: Optimistic | D4: Notes
A5: Volume per month (assets, campaigns, tickets) | B5: 15000 | C5: 15000 | D5: Units produced each month
A6: Cost per unit today | B6: 20 | C6: 20 | D6: Currency per unit
A7: Share of volume AI-assisted, year 1 after launch | B7: 0.35 | C7: 0.45
A8: Share of volume AI-assisted, year 2 | B8: 0.6 | C8: 0.75
A9: Share of volume AI-assisted, year 3 | B9: 0.8 | C9: 0.9 | D9: Applies to year 3 onward
A10: Cost saved per AI-assisted unit | B10: 0.35 | C10: 0.55 | D10: Share of unit cost
A11: Revenue affected per year | B11: 50000000 | C11: 50000000 | D11: For example email-driven revenue
A12: Margin on that revenue | B12: 0.3 | C12: 0.3 | D12: Contribution margin
A13: Uplift at full effect | B13: 0.01 | C13: 0.025 | D13: Share of revenue
A14: Share of uplift reached in year 1 | B14: 0.5 | C14: 0.5 | D14: Then 100% from year 2
A15: Build cost (total) | B15: 800000 | C15: 800000
A16: Build months | B16: 6 | C16: 6 | D16: Benefits start the month after build
A17: Run cost per year, from launch | B17: 280000 | C17: 280000
A18: Discount rate | B18: 0.12 | C18: 0.12 | D18: Annual
A19: Hurdle: breakeven within (months) | B19: 30 | C19: 30 | D19: Agree this before you calculate

Sheet Model
A1: Monthly model
A2: 36 months. Do not edit; change the Inputs sheet.
A4: Month | B4: Year index | C4: Pess: AI share | D4: Pess: cost saved | E4: Pess: uplift | F4: Pess: cost | G4: Pess: net | H4: Pess: cumulative | I4: Pess: discounted net | J4: Pess: breakeven flag | K4: Opt: AI share | L4: Opt: cost saved | M4: Opt: uplift | N4: Opt: cost | O4: Opt: net | P4: Opt: cumulative | Q4: Opt: discounted net | R4: Opt: breakeven flag
A5: 1 | B5: =IF(A5<=Inputs!$B$16,0,MIN(3,INT((A5-Inputs!$B$16-1)/12)+1)) -> 0 | C5: =CHOOSE($B5+1,0,Inputs!B7,Inputs!B8,Inputs!B9) -> 0 | D5: =Inputs!B5*Inputs!B6*C5*Inputs!B10 -> 0 | E5: =IF($B5=0,0,Inputs!B11*Inputs!B12*Inputs!B13/12*IF($B5=1,Inputs!B14,1)) -> 0 | F5: =IF($A5<=Inputs!B16,Inputs!B15/Inputs!B16,Inputs!B17/12) -> 133333.33 | G5: =D5+E5-F5 -> -133333.33 | H5: =G5 -> -133333.33 | I5: =G5/(1+Inputs!B18)^($A5/12) -> -132080.05 | J5: =IF(H5>0,$A5,"") | K5: =CHOOSE($B5+1,0,Inputs!C7,Inputs!C8,Inputs!C9) -> 0 | L5: =Inputs!C5*Inputs!C6*K5*Inputs!C10 -> 0 | M5: =IF($B5=0,0,Inputs!C11*Inputs!C12*Inputs!C13/12*IF($B5=1,Inputs!C14,1)) -> 0 | N5: =IF($A5<=Inputs!C16,Inputs!C15/Inputs!C16,Inputs!C17/12) -> 133333.33 | O5: =L5+M5-N5 -> -133333.33 | P5: =O5 -> -133333.33 | Q5: =O5/(1+Inputs!C18)^($A5/12) -> -132080.05 | R5: =IF(P5>0,$A5,"")
A6: 2 | B6: =IF(A6<=Inputs!$B$16,0,MIN(3,INT((A6-Inputs!$B$16-1)/12)+1)) -> 0 | C6: =CHOOSE($B6+1,0,Inputs!B7,Inputs!B8,Inputs!B9) -> 0 | D6: =Inputs!B5*Inputs!B6*C6*Inputs!B10 -> 0 | E6: =IF($B6=0,0,Inputs!B11*Inputs!B12*Inputs!B13/12*IF($B6=1,Inputs!B14,1)) -> 0 | F6: =IF($A6<=Inputs!B16,Inputs!B15/Inputs!B16,Inputs!B17/12) -> 133333.33 | G6: =D6+E6-F6 -> -133333.33 | H6: =H5+G6 -> -266666.67 | I6: =G6/(1+Inputs!B18)^($A6/12) -> -130838.55 | J6: =IF(H6>0,$A6,"") | K6: =CHOOSE($B6+1,0,Inputs!C7,Inputs!C8,Inputs!C9) -> 0 | L6: =Inputs!C5*Inputs!C6*K6*Inputs!C10 -> 0 | M6: =IF($B6=0,0,Inputs!C11*Inputs!C12*Inputs!C13/12*IF($B6=1,Inputs!C14,1)) -> 0 | N6: =IF($A6<=Inputs!C16,Inputs!C15/Inputs!C16,Inputs!C17/12) -> 133333.33 | O6: =L6+M6-N6 -> -133333.33 | P6: =P5+O6 -> -266666.67 | Q6: =O6/(1+Inputs!C18)^($A6/12) -> -130838.55 | R6: =IF(P6>0,$A6,"")
A7: 3 | B7: =IF(A7<=Inputs!$B$16,0,MIN(3,INT((A7-Inputs!$B$16-1)/12)+1)) -> 0 | C7: =CHOOSE($B7+1,0,Inputs!B7,Inputs!B8,Inputs!B9) -> 0 | D7: =Inputs!B5*Inputs!B6*C7*Inputs!B10 -> 0 | E7: =IF($B7=0,0,Inputs!B11*Inputs!B12*Inputs!B13/12*IF($B7=1,Inputs!B14,1)) -> 0 | F7: =IF($A7<=Inputs!B16,Inputs!B15/Inputs!B16,Inputs!B17/12) -> 133333.33 | G7: =D7+E7-F7 -> -133333.33 | H7: =H6+G7 -> -400000 | I7: =G7/(1+Inputs!B18)^($A7/12) -> -129608.72 | J7: =IF(H7>0,$A7,"") | K7: =CHOOSE($B7+1,0,Inputs!C7,Inputs!C8,Inputs!C9) -> 0 | L7: =Inputs!C5*Inputs!C6*K7*Inputs!C10 -> 0 | M7: =IF($B7=0,0,Inputs!C11*Inputs!C12*Inputs!C13/12*IF($B7=1,Inputs!C14,1)) -> 0 | N7: =IF($A7<=Inputs!C16,Inputs!C15/Inputs!C16,Inputs!C17/12) -> 133333.33 | O7: =L7+M7-N7 -> -133333.33 | P7: =P6+O7 -> -400000 | Q7: =O7/(1+Inputs!C18)^($A7/12) -> -129608.72 | R7: =IF(P7>0,$A7,"")
A8: 4 | B8: =IF(A8<=Inputs!$B$16,0,MIN(3,INT((A8-Inputs!$B$16-1)/12)+1)) -> 0 | C8: =CHOOSE($B8+1,0,Inputs!B7,Inputs!B8,Inputs!B9) -> 0 | D8: =Inputs!B5*Inputs!B6*C8*Inputs!B10 -> 0 | E8: =IF($B8=0,0,Inputs!B11*Inputs!B12*Inputs!B13/12*IF($B8=1,Inputs!B14,1)) -> 0 | F8: =IF($A8<=Inputs!B16,Inputs!B15/Inputs!B16,Inputs!B17/12) -> 133333.33 | G8: =D8+E8-F8 -> -133333.33 | H8: =H7+G8 -> -533333.33 | I8: =G8/(1+Inputs!B18)^($A8/12) -> -128390.45 | J8: =IF(H8>0,$A8,"") | K8: =CHOOSE($B8+1,0,Inputs!C7,Inputs!C8,Inputs!C9) -> 0 | L8: =Inputs!C5*Inputs!C6*K8*Inputs!C10 -> 0 | M8: =IF($B8=0,0,Inputs!C11*Inputs!C12*Inputs!C13/12*IF($B8=1,Inputs!C14,1)) -> 0 | N8: =IF($A8<=Inputs!C16,Inputs!C15/Inputs!C16,Inputs!C17/12) -> 133333.33 | O8: =L8+M8-N8 -> -133333.33 | P8: =P7+O8 -> -533333.33 | Q8: =O8/(1+Inputs!C18)^($A8/12) -> -128390.45 | R8: =IF(P8>0,$A8,"")
A9: 5 | B9: =IF(A9<=Inputs!$B$16,0,MIN(3,INT((A9-Inputs!$B$16-1)/12)+1)) -> 0 | C9: =CHOOSE($B9+1,0,Inputs!B7,Inputs!B8,Inputs!B9) -> 0 | D9: =Inputs!B5*Inputs!B6*C9*Inputs!B10 -> 0 | E9: =IF($B9=0,0,Inputs!B11*Inputs!B12*Inputs!B13/12*IF($B9=1,Inputs!B14,1)) -> 0 | F9: =IF($A9<=Inputs!B16,Inputs!B15/Inputs!B16,Inputs!B17/12) -> 133333.33 | G9: =D9+E9-F9 -> -133333.33 | H9: =H8+G9 -> -666666.67 | I9: =G9/(1+Inputs!B18)^($A9/12) -> -127183.63 | J9: =IF(H9>0,$A9,"") | K9: =CHOOSE($B9+1,0,Inputs!C7,Inputs!C8,Inputs!C9) -> 0 | L9: =Inputs!C5*Inputs!C6*K9*Inputs!C10 -> 0 | M9: =IF($B9=0,0,Inputs!C11*Inputs!C12*Inputs!C13/12*IF($B9=1,Inputs!C14,1)) -> 0 | N9: =IF($A9<=Inputs!C16,Inputs!C15/Inputs!C16,Inputs!C17/12) -> 133333.33 | O9: =L9+M9-N9 -> -133333.33 | P9: =P8+O9 -> -666666.67 | Q9: =O9/(1+Inputs!C18)^($A9/12) -> -127183.63 | R9: =IF(P9>0,$A9,"")
A10: 6 | B10: =IF(A10<=Inputs!$B$16,0,MIN(3,INT((A10-Inputs!$B$16-1)/12)+1)) -> 0 | C10: =CHOOSE($B10+1,0,Inputs!B7,Inputs!B8,Inputs!B9) -> 0 | D10: =Inputs!B5*Inputs!B6*C10*Inputs!B10 -> 0 | E10: =IF($B10=0,0,Inputs!B11*Inputs!B12*Inputs!B13/12*IF($B10=1,Inputs!B14,1)) -> 0 | F10: =IF($A10<=Inputs!B16,Inputs!B15/Inputs!B16,Inputs!B17/12) -> 133333.33 | G10: =D10+E10-F10 -> -133333.33 | H10: =H9+G10 -> -800000 | I10: =G10/(1+Inputs!B18)^($A10/12) -> -125988.16 | J10: =IF(H10>0,$A10,"") | K10: =CHOOSE($B10+1,0,Inputs!C7,Inputs!C8,Inputs!C9) -> 0 | L10: =Inputs!C5*Inputs!C6*K10*Inputs!C10 -> 0 | M10: =IF($B10=0,0,Inputs!C11*Inputs!C12*Inputs!C13/12*IF($B10=1,Inputs!C14,1)) -> 0 | N10: =IF($A10<=Inputs!C16,Inputs!C15/Inputs!C16,Inputs!C17/12) -> 133333.33 | O10: =L10+M10-N10 -> -133333.33 | P10: =P9+O10 -> -800000 | Q10: =O10/(1+Inputs!C18)^($A10/12) -> -125988.16 | R10: =IF(P10>0,$A10,"")
A11: 7 | B11: =IF(A11<=Inputs!$B$16,0,MIN(3,INT((A11-Inputs!$B$16-1)/12)+1)) -> 1 | C11: =CHOOSE($B11+1,0,Inputs!B7,Inputs!B8,Inputs!B9) -> 0.35 | D11: =Inputs!B5*Inputs!B6*C11*Inputs!B10 -> 36750 | E11: =IF($B11=0,0,Inputs!B11*Inputs!B12*Inputs!B13/12*IF($B11=1,Inputs!B14,1)) -> 6250 | F11: =IF($A11<=Inputs!B16,Inputs!B15/Inputs!B16,Inputs!B17/12) -> 23333.333 | G11: =D11+E11-F11 -> 19666.667 | H11: =H10+G11 -> -780333.33 | I11: =G11/(1+Inputs!B18)^($A11/12) -> 18408.578 | J11: =IF(H11>0,$A11,"") | K11: =CHOOSE($B11+1,0,Inputs!C7,Inputs!C8,Inputs!C9) -> 0.45 | L11: =Inputs!C5*Inputs!C6*K11*Inputs!C10 -> 74250 | M11: =IF($B11=0,0,Inputs!C11*Inputs!C12*Inputs!C13/12*IF($B11=1,Inputs!C14,1)) -> 15625 | N11: =IF($A11<=Inputs!C16,Inputs!C15/Inputs!C16,Inputs!C17/12) -> 23333.333 | O11: =L11+M11-N11 -> 66541.667 | P11: =P10+O11 -> -733458.33 | Q11: =O11/(1+Inputs!C18)^($A11/12) -> 62284.956 | R11: =IF(P11>0,$A11,"")
A12: 8 | B12: =IF(A12<=Inputs!$B$16,0,MIN(3,INT((A12-Inputs!$B$16-1)/12)+1)) -> 1 | C12: =CHOOSE($B12+1,0,Inputs!B7,Inputs!B8,Inputs!B9) -> 0.35 | D12: =Inputs!B5*Inputs!B6*C12*Inputs!B10 -> 36750 | E12: =IF($B12=0,0,Inputs!B11*Inputs!B12*Inputs!B13/12*IF($B12=1,Inputs!B14,1)) -> 6250 | F12: =IF($A12<=Inputs!B16,Inputs!B15/Inputs!B16,Inputs!B17/12) -> 23333.333 | G12: =D12+E12-F12 -> 19666.667 | H12: =H11+G12 -> -760666.67 | I12: =G12/(1+Inputs!B18)^($A12/12) -> 18235.545 | J12: =IF(H12>0,$A12,"") | K12: =CHOOSE($B12+1,0,Inputs!C7,Inputs!C8,Inputs!C9) -> 0.45 | L12: =Inputs!C5*Inputs!C6*K12*Inputs!C10 -> 74250 | M12: =IF($B12=0,0,Inputs!C11*Inputs!C12*Inputs!C13/12*IF($B12=1,Inputs!C14,1)) -> 15625 | N12: =IF($A12<=Inputs!C16,Inputs!C15/Inputs!C16,Inputs!C17/12) -> 23333.333 | O12: =L12+M12-N12 -> 66541.667 | P12: =P11+O12 -> -666916.67 | Q12: =O12/(1+Inputs!C18)^($A12/12) -> 61699.502 | R12: =IF(P12>0,$A12,"")
A13: 9 | B13: =IF(A13<=Inputs!$B$16,0,MIN(3,INT((A13-Inputs!$B$16-1)/12)+1)) -> 1 | C13: =CHOOSE($B13+1,0,Inputs!B7,Inputs!B8,Inputs!B9) -> 0.35 | D13: =Inputs!B5*Inputs!B6*C13*Inputs!B10 -> 36750 | E13: =IF($B13=0,0,Inputs!B11*Inputs!B12*Inputs!B13/12*IF($B13=1,Inputs!B14,1)) -> 6250 | F13: =IF($A13<=Inputs!B16,Inputs!B15/Inputs!B16,Inputs!B17/12) -> 23333.333 | G13: =D13+E13-F13 -> 19666.667 | H13: =H12+G13 -> -741000 | I13: =G13/(1+Inputs!B18)^($A13/12) -> 18064.138 | J13: =IF(H13>0,$A13,"") | K13: =CHOOSE($B13+1,0,Inputs!C7,Inputs!C8,Inputs!C9) -> 0.45 | L13: =Inputs!C5*Inputs!C6*K13*Inputs!C10 -> 74250 | M13: =IF($B13=0,0,Inputs!C11*Inputs!C12*Inputs!C13/12*IF($B13=1,Inputs!C14,1)) -> 15625 | N13: =IF($A13<=Inputs!C16,Inputs!C15/Inputs!C16,Inputs!C17/12) -> 23333.333 | O13: =L13+M13-N13 -> 66541.667 | P13: =P12+O13 -> -600375 | Q13: =O13/(1+Inputs!C18)^($A13/12) -> 61119.551 | R13: =IF(P13>0,$A13,"")
A14: 10 | B14: =IF(A14<=Inputs!$B$16,0,MIN(3,INT((A14-Inputs!$B$16-1)/12)+1)) -> 1 | C14: =CHOOSE($B14+1,0,Inputs!B7,Inputs!B8,Inputs!B9) -> 0.35 | D14: =Inputs!B5*Inputs!B6*C14*Inputs!B10 -> 36750 | E14: =IF($B14=0,0,Inputs!B11*Inputs!B12*Inputs!B13/12*IF($B14=1,Inputs!B14,1)) -> 6250 | F14: =IF($A14<=Inputs!B16,Inputs!B15/Inputs!B16,Inputs!B17/12) -> 23333.333 | G14: =D14+E14-F14 -> 19666.667 | H14: =H13+G14 -> -721333.33 | I14: =G14/(1+Inputs!B18)^($A14/12) -> 17894.342 | J14: =IF(H14>0,$A14,"") | K14: =CHOOSE($B14+1,0,Inputs!C7,Inputs!C8,Inputs!C9) -> 0.45 | L14: =Inputs!C5*Inputs!C6*K14*Inputs!C10 -> 74250 | M14: =IF($B14=0,0,Inputs!C11*Inputs!C12*Inputs!C13/12*IF($B14=1,Inputs!C14,1)) -> 15625 | N14: =IF($A14<=Inputs!C16,Inputs!C15/Inputs!C16,Inputs!C17/12) -> 23333.333 | O14: =L14+M14-N14 -> 66541.667 | P14: =P13+O14 -> -533833.33 | Q14: =O14/(1+Inputs!C18)^($A14/12) -> 60545.052 | R14: =IF(P14>0,$A14,"")
A15: 11 | B15: =IF(A15<=Inputs!$B$16,0,MIN(3,INT((A15-Inputs!$B$16-1)/12)+1)) -> 1 | C15: =CHOOSE($B15+1,0,Inputs!B7,Inputs!B8,Inputs!B9) -> 0.35 | D15: =Inputs!B5*Inputs!B6*C15*Inputs!B10 -> 36750 | E15: =IF($B15=0,0,Inputs!B11*Inputs!B12*Inputs!B13/12*IF($B15=1,Inputs!B14,1)) -> 6250 | F15: =IF($A15<=Inputs!B16,Inputs!B15/Inputs!B16,Inputs!B17/12) -> 23333.333 | G15: =D15+E15-F15 -> 19666.667 | H15: =H14+G15 -> -701666.67 | I15: =G15/(1+Inputs!B18)^($A15/12) -> 17726.142 | J15: =IF(H15>0,$A15,"") | K15: =CHOOSE($B15+1,0,Inputs!C7,Inputs!C8,Inputs!C9) -> 0.45 | L15: =Inputs!C5*Inputs!C6*K15*Inputs!C10 -> 74250 | M15: =IF($B15=0,0,Inputs!C11*Inputs!C12*Inputs!C13/12*IF($B15=1,Inputs!C14,1)) -> 15625 | N15: =IF($A15<=Inputs!C16,Inputs!C15/Inputs!C16,Inputs!C17/12) -> 23333.333 | O15: =L15+M15-N15 -> 66541.667 | P15: =P14+O15 -> -467291.67 | Q15: =O15/(1+Inputs!C18)^($A15/12) -> 59975.952 | R15: =IF(P15>0,$A15,"")
A16: 12 | B16: =IF(A16<=Inputs!$B$16,0,MIN(3,INT((A16-Inputs!$B$16-1)/12)+1)) -> 1 | C16: =CHOOSE($B16+1,0,Inputs!B7,Inputs!B8,Inputs!B9) -> 0.35 | D16: =Inputs!B5*Inputs!B6*C16*Inputs!B10 -> 36750 | E16: =IF($B16=0,0,Inputs!B11*Inputs!B12*Inputs!B13/12*IF($B16=1,Inputs!B14,1)) -> 6250 | F16: =IF($A16<=Inputs!B16,Inputs!B15/Inputs!B16,Inputs!B17/12) -> 23333.333 | G16: =D16+E16-F16 -> 19666.667 | H16: =H15+G16 -> -682000 | I16: =G16/(1+Inputs!B18)^($A16/12) -> 17559.524 | J16: =IF(H16>0,$A16,"") | K16: =CHOOSE($B16+1,0,Inputs!C7,Inputs!C8,Inputs!C9) -> 0.45 | L16: =Inputs!C5*Inputs!C6*K16*Inputs!C10 -> 74250 | M16: =IF($B16=0,0,Inputs!C11*Inputs!C12*Inputs!C13/12*IF($B16=1,Inputs!C14,1)) -> 15625 | N16: =IF($A16<=Inputs!C16,Inputs!C15/Inputs!C16,Inputs!C17/12) -> 23333.333 | O16: =L16+M16-N16 -> 66541.667 | P16: =P15+O16 -> -400750 | Q16: =O16/(1+Inputs!C18)^($A16/12) -> 59412.202 | R16: =IF(P16>0,$A16,"")
A17: 13 | B17: =IF(A17<=Inputs!$B$16,0,MIN(3,INT((A17-Inputs!$B$16-1)/12)+1)) -> 1 | C17: =CHOOSE($B17+1,0,Inputs!B7,Inputs!B8,Inputs!B9) -> 0.35 | D17: =Inputs!B5*Inputs!B6*C17*Inputs!B10 -> 36750 | E17: =IF($B17=0,0,Inputs!B11*Inputs!B12*Inputs!B13/12*IF($B17=1,Inputs!B14,1)) -> 6250 | F17: =IF($A17<=Inputs!B16,Inputs!B15/Inputs!B16,Inputs!B17/12) -> 23333.333 | G17: =D17+E17-F17 -> 19666.667 | H17: =H16+G17 -> -662333.33 | I17: =G17/(1+Inputs!B18)^($A17/12) -> 17394.471 | J17: =IF(H17>0,$A17,"") | K17: =CHOOSE($B17+1,0,Inputs!C7,Inputs!C8,Inputs!C9) -> 0.45 | L17: =Inputs!C5*Inputs!C6*K17*Inputs!C10 -> 74250 | M17: =IF($B17=0,0,Inputs!C11*Inputs!C12*Inputs!C13/12*IF($B17=1,Inputs!C14,1)) -> 15625 | N17: =IF($A17<=Inputs!C16,Inputs!C15/Inputs!C16,Inputs!C17/12) -> 23333.333 | O17: =L17+M17-N17 -> 66541.667 | P17: =P16+O17 -> -334208.33 | Q17: =O17/(1+Inputs!C18)^($A17/12) -> 58853.751 | R17: =IF(P17>0,$A17,"")
A18: 14 | B18: =IF(A18<=Inputs!$B$16,0,MIN(3,INT((A18-Inputs!$B$16-1)/12)+1)) -> 1 | C18: =CHOOSE($B18+1,0,Inputs!B7,Inputs!B8,Inputs!B9) -> 0.35 | D18: =Inputs!B5*Inputs!B6*C18*Inputs!B10 -> 36750 | E18: =IF($B18=0,0,Inputs!B11*Inputs!B12*Inputs!B13/12*IF($B18=1,Inputs!B14,1)) -> 6250 | F18: =IF($A18<=Inputs!B16,Inputs!B15/Inputs!B16,Inputs!B17/12) -> 23333.333 | G18: =D18+E18-F18 -> 19666.667 | H18: =H17+G18 -> -642666.67 | I18: =G18/(1+Inputs!B18)^($A18/12) -> 17230.97 | J18: =IF(H18>0,$A18,"") | K18: =CHOOSE($B18+1,0,Inputs!C7,Inputs!C8,Inputs!C9) -> 0.45 | L18: =Inputs!C5*Inputs!C6*K18*Inputs!C10 -> 74250 | M18: =IF($B18=0,0,Inputs!C11*Inputs!C12*Inputs!C13/12*IF($B18=1,Inputs!C14,1)) -> 15625 | N18: =IF($A18<=Inputs!C16,Inputs!C15/Inputs!C16,Inputs!C17/12) -> 23333.333 | O18: =L18+M18-N18 -> 66541.667 | P18: =P17+O18 -> -267666.67 | Q18: =O18/(1+Inputs!C18)^($A18/12) -> 58300.549 | R18: =IF(P18>0,$A18,"")
A19: 15 | B19: =IF(A19<=Inputs!$B$16,0,MIN(3,INT((A19-Inputs!$B$16-1)/12)+1)) -> 1 | C19: =CHOOSE($B19+1,0,Inputs!B7,Inputs!B8,Inputs!B9) -> 0.35 | D19: =Inputs!B5*Inputs!B6*C19*Inputs!B10 -> 36750 | E19: =IF($B19=0,0,Inputs!B11*Inputs!B12*Inputs!B13/12*IF($B19=1,Inputs!B14,1)) -> 6250 | F19: =IF($A19<=Inputs!B16,Inputs!B15/Inputs!B16,Inputs!B17/12) -> 23333.333 | G19: =D19+E19-F19 -> 19666.667 | H19: =H18+G19 -> -623000 | I19: =G19/(1+Inputs!B18)^($A19/12) -> 17069.006 | J19: =IF(H19>0,$A19,"") | K19: =CHOOSE($B19+1,0,Inputs!C7,Inputs!C8,Inputs!C9) -> 0.45 | L19: =Inputs!C5*Inputs!C6*K19*Inputs!C10 -> 74250 | M19: =IF($B19=0,0,Inputs!C11*Inputs!C12*Inputs!C13/12*IF($B19=1,Inputs!C14,1)) -> 15625 | N19: =IF($A19<=Inputs!C16,Inputs!C15/Inputs!C16,Inputs!C17/12) -> 23333.333 | O19: =L19+M19-N19 -> 66541.667 | P19: =P18+O19 -> -201125 | Q19: =O19/(1+Inputs!C18)^($A19/12) -> 57752.548 | R19: =IF(P19>0,$A19,"")
A20: 16 | B20: =IF(A20<=Inputs!$B$16,0,MIN(3,INT((A20-Inputs!$B$16-1)/12)+1)) -> 1 | C20: =CHOOSE($B20+1,0,Inputs!B7,Inputs!B8,Inputs!B9) -> 0.35 | D20: =Inputs!B5*Inputs!B6*C20*Inputs!B10 -> 36750 | E20: =IF($B20=0,0,Inputs!B11*Inputs!B12*Inputs!B13/12*IF($B20=1,Inputs!B14,1)) -> 6250 | F20: =IF($A20<=Inputs!B16,Inputs!B15/Inputs!B16,Inputs!B17/12) -> 23333.333 | G20: =D20+E20-F20 -> 19666.667 | H20: =H19+G20 -> -603333.33 | I20: =G20/(1+Inputs!B18)^($A20/12) -> 16908.564 | J20: =IF(H20>0,$A20,"") | K20: =CHOOSE($B20+1,0,Inputs!C7,Inputs!C8,Inputs!C9) -> 0.45 | L20: =Inputs!C5*Inputs!C6*K20*Inputs!C10 -> 74250 | M20: =IF($B20=0,0,Inputs!C11*Inputs!C12*Inputs!C13/12*IF($B20=1,Inputs!C14,1)) -> 15625 | N20: =IF($A20<=Inputs!C16,Inputs!C15/Inputs!C16,Inputs!C17/12) -> 23333.333 | O20: =L20+M20-N20 -> 66541.667 | P20: =P19+O20 -> -134583.33 | Q20: =O20/(1+Inputs!C18)^($A20/12) -> 57209.697 | R20: =IF(P20>0,$A20,"")
A21: 17 | B21: =IF(A21<=Inputs!$B$16,0,MIN(3,INT((A21-Inputs!$B$16-1)/12)+1)) -> 1 | C21: =CHOOSE($B21+1,0,Inputs!B7,Inputs!B8,Inputs!B9) -> 0.35 | D21: =Inputs!B5*Inputs!B6*C21*Inputs!B10 -> 36750 | E21: =IF($B21=0,0,Inputs!B11*Inputs!B12*Inputs!B13/12*IF($B21=1,Inputs!B14,1)) -> 6250 | F21: =IF($A21<=Inputs!B16,Inputs!B15/Inputs!B16,Inputs!B17/12) -> 23333.333 | G21: =D21+E21-F21 -> 19666.667 | H21: =H20+G21 -> -583666.67 | I21: =G21/(1+Inputs!B18)^($A21/12) -> 16749.63 | J21: =IF(H21>0,$A21,"") | K21: =CHOOSE($B21+1,0,Inputs!C7,Inputs!C8,Inputs!C9) -> 0.45 | L21: =Inputs!C5*Inputs!C6*K21*Inputs!C10 -> 74250 | M21: =IF($B21=0,0,Inputs!C11*Inputs!C12*Inputs!C13/12*IF($B21=1,Inputs!C14,1)) -> 15625 | N21: =IF($A21<=Inputs!C16,Inputs!C15/Inputs!C16,Inputs!C17/12) -> 23333.333 | O21: =L21+M21-N21 -> 66541.667 | P21: =P20+O21 -> -68041.667 | Q21: =O21/(1+Inputs!C18)^($A21/12) -> 56671.948 | R21: =IF(P21>0,$A21,"")
A22: 18 | B22: =IF(A22<=Inputs!$B$16,0,MIN(3,INT((A22-Inputs!$B$16-1)/12)+1)) -> 1 | C22: =CHOOSE($B22+1,0,Inputs!B7,Inputs!B8,Inputs!B9) -> 0.35 | D22: =Inputs!B5*Inputs!B6*C22*Inputs!B10 -> 36750 | E22: =IF($B22=0,0,Inputs!B11*Inputs!B12*Inputs!B13/12*IF($B22=1,Inputs!B14,1)) -> 6250 | F22: =IF($A22<=Inputs!B16,Inputs!B15/Inputs!B16,Inputs!B17/12) -> 23333.333 | G22: =D22+E22-F22 -> 19666.667 | H22: =H21+G22 -> -564000 | I22: =G22/(1+Inputs!B18)^($A22/12) -> 16592.19 | J22: =IF(H22>0,$A22,"") | K22: =CHOOSE($B22+1,0,Inputs!C7,Inputs!C8,Inputs!C9) -> 0.45 | L22: =Inputs!C5*Inputs!C6*K22*Inputs!C10 -> 74250 | M22: =IF($B22=0,0,Inputs!C11*Inputs!C12*Inputs!C13/12*IF($B22=1,Inputs!C14,1)) -> 15625 | N22: =IF($A22<=Inputs!C16,Inputs!C15/Inputs!C16,Inputs!C17/12) -> 23333.333 | O22: =L22+M22-N22 -> 66541.667 | P22: =P21+O22 -> -1500 | Q22: =O22/(1+Inputs!C18)^($A22/12) -> 56139.254 | R22: =IF(P22>0,$A22,"")
A23: 19 | B23: =IF(A23<=Inputs!$B$16,0,MIN(3,INT((A23-Inputs!$B$16-1)/12)+1)) -> 2 | C23: =CHOOSE($B23+1,0,Inputs!B7,Inputs!B8,Inputs!B9) -> 0.6 | D23: =Inputs!B5*Inputs!B6*C23*Inputs!B10 -> 63000 | E23: =IF($B23=0,0,Inputs!B11*Inputs!B12*Inputs!B13/12*IF($B23=1,Inputs!B14,1)) -> 12500 | F23: =IF($A23<=Inputs!B16,Inputs!B15/Inputs!B16,Inputs!B17/12) -> 23333.333 | G23: =D23+E23-F23 -> 52166.667 | H23: =H22+G23 -> -511833.33 | I23: =G23/(1+Inputs!B18)^($A23/12) -> 43597.798 | J23: =IF(H23>0,$A23,"") | K23: =CHOOSE($B23+1,0,Inputs!C7,Inputs!C8,Inputs!C9) -> 0.75 | L23: =Inputs!C5*Inputs!C6*K23*Inputs!C10 -> 123750 | M23: =IF($B23=0,0,Inputs!C11*Inputs!C12*Inputs!C13/12*IF($B23=1,Inputs!C14,1)) -> 31250 | N23: =IF($A23<=Inputs!C16,Inputs!C15/Inputs!C16,Inputs!C17/12) -> 23333.333 | O23: =L23+M23-N23 -> 131666.67 | P23: =P22+O23 -> 130166.67 | Q23: =O23/(1+Inputs!C18)^($A23/12) -> 110039.17 | R23: =IF(P23>0,$A23,"") -> 19
A24: 20 | B24: =IF(A24<=Inputs!$B$16,0,MIN(3,INT((A24-Inputs!$B$16-1)/12)+1)) -> 2 | C24: =CHOOSE($B24+1,0,Inputs!B7,Inputs!B8,Inputs!B9) -> 0.6 | D24: =Inputs!B5*Inputs!B6*C24*Inputs!B10 -> 63000 | E24: =IF($B24=0,0,Inputs!B11*Inputs!B12*Inputs!B13/12*IF($B24=1,Inputs!B14,1)) -> 12500 | F24: =IF($A24<=Inputs!B16,Inputs!B15/Inputs!B16,Inputs!B17/12) -> 23333.333 | G24: =D24+E24-F24 -> 52166.667 | H24: =H23+G24 -> -459666.67 | I24: =G24/(1+Inputs!B18)^($A24/12) -> 43187.996 | J24: =IF(H24>0,$A24,"") | K24: =CHOOSE($B24+1,0,Inputs!C7,Inputs!C8,Inputs!C9) -> 0.75 | L24: =Inputs!C5*Inputs!C6*K24*Inputs!C10 -> 123750 | M24: =IF($B24=0,0,Inputs!C11*Inputs!C12*Inputs!C13/12*IF($B24=1,Inputs!C14,1)) -> 31250 | N24: =IF($A24<=Inputs!C16,Inputs!C15/Inputs!C16,Inputs!C17/12) -> 23333.333 | O24: =L24+M24-N24 -> 131666.67 | P24: =P23+O24 -> 261833.33 | Q24: =O24/(1+Inputs!C18)^($A24/12) -> 109004.85 | R24: =IF(P24>0,$A24,"") -> 20
A25: 21 | B25: =IF(A25<=Inputs!$B$16,0,MIN(3,INT((A25-Inputs!$B$16-1)/12)+1)) -> 2 | C25: =CHOOSE($B25+1,0,Inputs!B7,Inputs!B8,Inputs!B9) -> 0.6 | D25: =Inputs!B5*Inputs!B6*C25*Inputs!B10 -> 63000 | E25: =IF($B25=0,0,Inputs!B11*Inputs!B12*Inputs!B13/12*IF($B25=1,Inputs!B14,1)) -> 12500 | F25: =IF($A25<=Inputs!B16,Inputs!B15/Inputs!B16,Inputs!B17/12) -> 23333.333 | G25: =D25+E25-F25 -> 52166.667 | H25: =H24+G25 -> -407500 | I25: =G25/(1+Inputs!B18)^($A25/12) -> 42782.046 | J25: =IF(H25>0,$A25,"") | K25: =CHOOSE($B25+1,0,Inputs!C7,Inputs!C8,Inputs!C9) -> 0.75 | L25: =Inputs!C5*Inputs!C6*K25*Inputs!C10 -> 123750 | M25: =IF($B25=0,0,Inputs!C11*Inputs!C12*Inputs!C13/12*IF($B25=1,Inputs!C14,1)) -> 31250 | N25: =IF($A25<=Inputs!C16,Inputs!C15/Inputs!C16,Inputs!C17/12) -> 23333.333 | O25: =L25+M25-N25 -> 131666.67 | P25: =P24+O25 -> 393500 | Q25: =O25/(1+Inputs!C18)^($A25/12) -> 107980.24 | R25: =IF(P25>0,$A25,"") -> 21
A26: 22 | B26: =IF(A26<=Inputs!$B$16,0,MIN(3,INT((A26-Inputs!$B$16-1)/12)+1)) -> 2 | C26: =CHOOSE($B26+1,0,Inputs!B7,Inputs!B8,Inputs!B9) -> 0.6 | D26: =Inputs!B5*Inputs!B6*C26*Inputs!B10 -> 63000 | E26: =IF($B26=0,0,Inputs!B11*Inputs!B12*Inputs!B13/12*IF($B26=1,Inputs!B14,1)) -> 12500 | F26: =IF($A26<=Inputs!B16,Inputs!B15/Inputs!B16,Inputs!B17/12) -> 23333.333 | G26: =D26+E26-F26 -> 52166.667 | H26: =H25+G26 -> -355333.33 | I26: =G26/(1+Inputs!B18)^($A26/12) -> 42379.912 | J26: =IF(H26>0,$A26,"") | K26: =CHOOSE($B26+1,0,Inputs!C7,Inputs!C8,Inputs!C9) -> 0.75 | L26: =Inputs!C5*Inputs!C6*K26*Inputs!C10 -> 123750 | M26: =IF($B26=0,0,Inputs!C11*Inputs!C12*Inputs!C13/12*IF($B26=1,Inputs!C14,1)) -> 31250 | N26: =IF($A26<=Inputs!C16,Inputs!C15/Inputs!C16,Inputs!C17/12) -> 23333.333 | O26: =L26+M26-N26 -> 131666.67 | P26: =P25+O26 -> 525166.67 | Q26: =O26/(1+Inputs!C18)^($A26/12) -> 106965.27 | R26: =IF(P26>0,$A26,"") -> 22
A27: 23 | B27: =IF(A27<=Inputs!$B$16,0,MIN(3,INT((A27-Inputs!$B$16-1)/12)+1)) -> 2 | C27: =CHOOSE($B27+1,0,Inputs!B7,Inputs!B8,Inputs!B9) -> 0.6 | D27: =Inputs!B5*Inputs!B6*C27*Inputs!B10 -> 63000 | E27: =IF($B27=0,0,Inputs!B11*Inputs!B12*Inputs!B13/12*IF($B27=1,Inputs!B14,1)) -> 12500 | F27: =IF($A27<=Inputs!B16,Inputs!B15/Inputs!B16,Inputs!B17/12) -> 23333.333 | G27: =D27+E27-F27 -> 52166.667 | H27: =H26+G27 -> -303166.67 | I27: =G27/(1+Inputs!B18)^($A27/12) -> 41981.557 | J27: =IF(H27>0,$A27,"") | K27: =CHOOSE($B27+1,0,Inputs!C7,Inputs!C8,Inputs!C9) -> 0.75 | L27: =Inputs!C5*Inputs!C6*K27*Inputs!C10 -> 123750 | M27: =IF($B27=0,0,Inputs!C11*Inputs!C12*Inputs!C13/12*IF($B27=1,Inputs!C14,1)) -> 31250 | N27: =IF($A27<=Inputs!C16,Inputs!C15/Inputs!C16,Inputs!C17/12) -> 23333.333 | O27: =L27+M27-N27 -> 131666.67 | P27: =P26+O27 -> 656833.33 | Q27: =O27/(1+Inputs!C18)^($A27/12) -> 105959.84 | R27: =IF(P27>0,$A27,"") -> 23
A28: 24 | B28: =IF(A28<=Inputs!$B$16,0,MIN(3,INT((A28-Inputs!$B$16-1)/12)+1)) -> 2 | C28: =CHOOSE($B28+1,0,Inputs!B7,Inputs!B8,Inputs!B9) -> 0.6 | D28: =Inputs!B5*Inputs!B6*C28*Inputs!B10 -> 63000 | E28: =IF($B28=0,0,Inputs!B11*Inputs!B12*Inputs!B13/12*IF($B28=1,Inputs!B14,1)) -> 12500 | F28: =IF($A28<=Inputs!B16,Inputs!B15/Inputs!B16,Inputs!B17/12) -> 23333.333 | G28: =D28+E28-F28 -> 52166.667 | H28: =H27+G28 -> -251000 | I28: =G28/(1+Inputs!B18)^($A28/12) -> 41586.947 | J28: =IF(H28>0,$A28,"") | K28: =CHOOSE($B28+1,0,Inputs!C7,Inputs!C8,Inputs!C9) -> 0.75 | L28: =Inputs!C5*Inputs!C6*K28*Inputs!C10 -> 123750 | M28: =IF($B28=0,0,Inputs!C11*Inputs!C12*Inputs!C13/12*IF($B28=1,Inputs!C14,1)) -> 31250 | N28: =IF($A28<=Inputs!C16,Inputs!C15/Inputs!C16,Inputs!C17/12) -> 23333.333 | O28: =L28+M28-N28 -> 131666.67 | P28: =P27+O28 -> 788500 | Q28: =O28/(1+Inputs!C18)^($A28/12) -> 104963.86 | R28: =IF(P28>0,$A28,"") -> 24
A29: 25 | B29: =IF(A29<=Inputs!$B$16,0,MIN(3,INT((A29-Inputs!$B$16-1)/12)+1)) -> 2 | C29: =CHOOSE($B29+1,0,Inputs!B7,Inputs!B8,Inputs!B9) -> 0.6 | D29: =Inputs!B5*Inputs!B6*C29*Inputs!B10 -> 63000 | E29: =IF($B29=0,0,Inputs!B11*Inputs!B12*Inputs!B13/12*IF($B29=1,Inputs!B14,1)) -> 12500 | F29: =IF($A29<=Inputs!B16,Inputs!B15/Inputs!B16,Inputs!B17/12) -> 23333.333 | G29: =D29+E29-F29 -> 52166.667 | H29: =H28+G29 -> -198833.33 | I29: =G29/(1+Inputs!B18)^($A29/12) -> 41196.047 | J29: =IF(H29>0,$A29,"") | K29: =CHOOSE($B29+1,0,Inputs!C7,Inputs!C8,Inputs!C9) -> 0.75 | L29: =Inputs!C5*Inputs!C6*K29*Inputs!C10 -> 123750 | M29: =IF($B29=0,0,Inputs!C11*Inputs!C12*Inputs!C13/12*IF($B29=1,Inputs!C14,1)) -> 31250 | N29: =IF($A29<=Inputs!C16,Inputs!C15/Inputs!C16,Inputs!C17/12) -> 23333.333 | O29: =L29+M29-N29 -> 131666.67 | P29: =P28+O29 -> 920166.67 | Q29: =O29/(1+Inputs!C18)^($A29/12) -> 103977.24 | R29: =IF(P29>0,$A29,"") -> 25
A30: 26 | B30: =IF(A30<=Inputs!$B$16,0,MIN(3,INT((A30-Inputs!$B$16-1)/12)+1)) -> 2 | C30: =CHOOSE($B30+1,0,Inputs!B7,Inputs!B8,Inputs!B9) -> 0.6 | D30: =Inputs!B5*Inputs!B6*C30*Inputs!B10 -> 63000 | E30: =IF($B30=0,0,Inputs!B11*Inputs!B12*Inputs!B13/12*IF($B30=1,Inputs!B14,1)) -> 12500 | F30: =IF($A30<=Inputs!B16,Inputs!B15/Inputs!B16,Inputs!B17/12) -> 23333.333 | G30: =D30+E30-F30 -> 52166.667 | H30: =H29+G30 -> -146666.67 | I30: =G30/(1+Inputs!B18)^($A30/12) -> 40808.82 | J30: =IF(H30>0,$A30,"") | K30: =CHOOSE($B30+1,0,Inputs!C7,Inputs!C8,Inputs!C9) -> 0.75 | L30: =Inputs!C5*Inputs!C6*K30*Inputs!C10 -> 123750 | M30: =IF($B30=0,0,Inputs!C11*Inputs!C12*Inputs!C13/12*IF($B30=1,Inputs!C14,1)) -> 31250 | N30: =IF($A30<=Inputs!C16,Inputs!C15/Inputs!C16,Inputs!C17/12) -> 23333.333 | O30: =L30+M30-N30 -> 131666.67 | P30: =P29+O30 -> 1051833.3 | Q30: =O30/(1+Inputs!C18)^($A30/12) -> 102999.9 | R30: =IF(P30>0,$A30,"") -> 26
A31: 27 | B31: =IF(A31<=Inputs!$B$16,0,MIN(3,INT((A31-Inputs!$B$16-1)/12)+1)) -> 2 | C31: =CHOOSE($B31+1,0,Inputs!B7,Inputs!B8,Inputs!B9) -> 0.6 | D31: =Inputs!B5*Inputs!B6*C31*Inputs!B10 -> 63000 | E31: =IF($B31=0,0,Inputs!B11*Inputs!B12*Inputs!B13/12*IF($B31=1,Inputs!B14,1)) -> 12500 | F31: =IF($A31<=Inputs!B16,Inputs!B15/Inputs!B16,Inputs!B17/12) -> 23333.333 | G31: =D31+E31-F31 -> 52166.667 | H31: =H30+G31 -> -94500 | I31: =G31/(1+Inputs!B18)^($A31/12) -> 40425.233 | J31: =IF(H31>0,$A31,"") | K31: =CHOOSE($B31+1,0,Inputs!C7,Inputs!C8,Inputs!C9) -> 0.75 | L31: =Inputs!C5*Inputs!C6*K31*Inputs!C10 -> 123750 | M31: =IF($B31=0,0,Inputs!C11*Inputs!C12*Inputs!C13/12*IF($B31=1,Inputs!C14,1)) -> 31250 | N31: =IF($A31<=Inputs!C16,Inputs!C15/Inputs!C16,Inputs!C17/12) -> 23333.333 | O31: =L31+M31-N31 -> 131666.67 | P31: =P30+O31 -> 1183500 | Q31: =O31/(1+Inputs!C18)^($A31/12) -> 102031.74 | R31: =IF(P31>0,$A31,"") -> 27
A32: 28 | B32: =IF(A32<=Inputs!$B$16,0,MIN(3,INT((A32-Inputs!$B$16-1)/12)+1)) -> 2 | C32: =CHOOSE($B32+1,0,Inputs!B7,Inputs!B8,Inputs!B9) -> 0.6 | D32: =Inputs!B5*Inputs!B6*C32*Inputs!B10 -> 63000 | E32: =IF($B32=0,0,Inputs!B11*Inputs!B12*Inputs!B13/12*IF($B32=1,Inputs!B14,1)) -> 12500 | F32: =IF($A32<=Inputs!B16,Inputs!B15/Inputs!B16,Inputs!B17/12) -> 23333.333 | G32: =D32+E32-F32 -> 52166.667 | H32: =H31+G32 -> -42333.333 | I32: =G32/(1+Inputs!B18)^($A32/12) -> 40045.252 | J32: =IF(H32>0,$A32,"") | K32: =CHOOSE($B32+1,0,Inputs!C7,Inputs!C8,Inputs!C9) -> 0.75 | L32: =Inputs!C5*Inputs!C6*K32*Inputs!C10 -> 123750 | M32: =IF($B32=0,0,Inputs!C11*Inputs!C12*Inputs!C13/12*IF($B32=1,Inputs!C14,1)) -> 31250 | N32: =IF($A32<=Inputs!C16,Inputs!C15/Inputs!C16,Inputs!C17/12) -> 23333.333 | O32: =L32+M32-N32 -> 131666.67 | P32: =P31+O32 -> 1315166.7 | Q32: =O32/(1+Inputs!C18)^($A32/12) -> 101072.68 | R32: =IF(P32>0,$A32,"") -> 28
A33: 29 | B33: =IF(A33<=Inputs!$B$16,0,MIN(3,INT((A33-Inputs!$B$16-1)/12)+1)) -> 2 | C33: =CHOOSE($B33+1,0,Inputs!B7,Inputs!B8,Inputs!B9) -> 0.6 | D33: =Inputs!B5*Inputs!B6*C33*Inputs!B10 -> 63000 | E33: =IF($B33=0,0,Inputs!B11*Inputs!B12*Inputs!B13/12*IF($B33=1,Inputs!B14,1)) -> 12500 | F33: =IF($A33<=Inputs!B16,Inputs!B15/Inputs!B16,Inputs!B17/12) -> 23333.333 | G33: =D33+E33-F33 -> 52166.667 | H33: =H32+G33 -> 9833.3333 | I33: =G33/(1+Inputs!B18)^($A33/12) -> 39668.843 | J33: =IF(H33>0,$A33,"") -> 29 | K33: =CHOOSE($B33+1,0,Inputs!C7,Inputs!C8,Inputs!C9) -> 0.75 | L33: =Inputs!C5*Inputs!C6*K33*Inputs!C10 -> 123750 | M33: =IF($B33=0,0,Inputs!C11*Inputs!C12*Inputs!C13/12*IF($B33=1,Inputs!C14,1)) -> 31250 | N33: =IF($A33<=Inputs!C16,Inputs!C15/Inputs!C16,Inputs!C17/12) -> 23333.333 | O33: =L33+M33-N33 -> 131666.67 | P33: =P32+O33 -> 1446833.3 | Q33: =O33/(1+Inputs!C18)^($A33/12) -> 100122.64 | R33: =IF(P33>0,$A33,"") -> 29
A34: 30 | B34: =IF(A34<=Inputs!$B$16,0,MIN(3,INT((A34-Inputs!$B$16-1)/12)+1)) -> 2 | C34: =CHOOSE($B34+1,0,Inputs!B7,Inputs!B8,Inputs!B9) -> 0.6 | D34: =Inputs!B5*Inputs!B6*C34*Inputs!B10 -> 63000 | E34: =IF($B34=0,0,Inputs!B11*Inputs!B12*Inputs!B13/12*IF($B34=1,Inputs!B14,1)) -> 12500 | F34: =IF($A34<=Inputs!B16,Inputs!B15/Inputs!B16,Inputs!B17/12) -> 23333.333 | G34: =D34+E34-F34 -> 52166.667 | H34: =H33+G34 -> 62000 | I34: =G34/(1+Inputs!B18)^($A34/12) -> 39295.972 | J34: =IF(H34>0,$A34,"") -> 30 | K34: =CHOOSE($B34+1,0,Inputs!C7,Inputs!C8,Inputs!C9) -> 0.75 | L34: =Inputs!C5*Inputs!C6*K34*Inputs!C10 -> 123750 | M34: =IF($B34=0,0,Inputs!C11*Inputs!C12*Inputs!C13/12*IF($B34=1,Inputs!C14,1)) -> 31250 | N34: =IF($A34<=Inputs!C16,Inputs!C15/Inputs!C16,Inputs!C17/12) -> 23333.333 | O34: =L34+M34-N34 -> 131666.67 | P34: =P33+O34 -> 1578500 | Q34: =O34/(1+Inputs!C18)^($A34/12) -> 99181.526 | R34: =IF(P34>0,$A34,"") -> 30
A35: 31 | B35: =IF(A35<=Inputs!$B$16,0,MIN(3,INT((A35-Inputs!$B$16-1)/12)+1)) -> 3 | C35: =CHOOSE($B35+1,0,Inputs!B7,Inputs!B8,Inputs!B9) -> 0.8 | D35: =Inputs!B5*Inputs!B6*C35*Inputs!B10 -> 84000 | E35: =IF($B35=0,0,Inputs!B11*Inputs!B12*Inputs!B13/12*IF($B35=1,Inputs!B14,1)) -> 12500 | F35: =IF($A35<=Inputs!B16,Inputs!B15/Inputs!B16,Inputs!B17/12) -> 23333.333 | G35: =D35+E35-F35 -> 73166.667 | H35: =H34+G35 -> 135166.67 | I35: =G35/(1+Inputs!B18)^($A35/12) -> 54596.74 | J35: =IF(H35>0,$A35,"") -> 31 | K35: =CHOOSE($B35+1,0,Inputs!C7,Inputs!C8,Inputs!C9) -> 0.9 | L35: =Inputs!C5*Inputs!C6*K35*Inputs!C10 -> 148500 | M35: =IF($B35=0,0,Inputs!C11*Inputs!C12*Inputs!C13/12*IF($B35=1,Inputs!C14,1)) -> 31250 | N35: =IF($A35<=Inputs!C16,Inputs!C15/Inputs!C16,Inputs!C17/12) -> 23333.333 | O35: =L35+M35-N35 -> 156416.67 | P35: =P34+O35 -> 1734916.7 | Q35: =O35/(1+Inputs!C18)^($A35/12) -> 116717.63 | R35: =IF(P35>0,$A35,"") -> 31
A36: 32 | B36: =IF(A36<=Inputs!$B$16,0,MIN(3,INT((A36-Inputs!$B$16-1)/12)+1)) -> 3 | C36: =CHOOSE($B36+1,0,Inputs!B7,Inputs!B8,Inputs!B9) -> 0.8 | D36: =Inputs!B5*Inputs!B6*C36*Inputs!B10 -> 84000 | E36: =IF($B36=0,0,Inputs!B11*Inputs!B12*Inputs!B13/12*IF($B36=1,Inputs!B14,1)) -> 12500 | F36: =IF($A36<=Inputs!B16,Inputs!B15/Inputs!B16,Inputs!B17/12) -> 23333.333 | G36: =D36+E36-F36 -> 73166.667 | H36: =H35+G36 -> 208333.33 | I36: =G36/(1+Inputs!B18)^($A36/12) -> 54083.552 | J36: =IF(H36>0,$A36,"") -> 32 | K36: =CHOOSE($B36+1,0,Inputs!C7,Inputs!C8,Inputs!C9) -> 0.9 | L36: =Inputs!C5*Inputs!C6*K36*Inputs!C10 -> 148500 | M36: =IF($B36=0,0,Inputs!C11*Inputs!C12*Inputs!C13/12*IF($B36=1,Inputs!C14,1)) -> 31250 | N36: =IF($A36<=Inputs!C16,Inputs!C15/Inputs!C16,Inputs!C17/12) -> 23333.333 | O36: =L36+M36-N36 -> 156416.67 | P36: =P35+O36 -> 1891333.3 | Q36: =O36/(1+Inputs!C18)^($A36/12) -> 115620.53 | R36: =IF(P36>0,$A36,"") -> 32
A37: 33 | B37: =IF(A37<=Inputs!$B$16,0,MIN(3,INT((A37-Inputs!$B$16-1)/12)+1)) -> 3 | C37: =CHOOSE($B37+1,0,Inputs!B7,Inputs!B8,Inputs!B9) -> 0.8 | D37: =Inputs!B5*Inputs!B6*C37*Inputs!B10 -> 84000 | E37: =IF($B37=0,0,Inputs!B11*Inputs!B12*Inputs!B13/12*IF($B37=1,Inputs!B14,1)) -> 12500 | F37: =IF($A37<=Inputs!B16,Inputs!B15/Inputs!B16,Inputs!B17/12) -> 23333.333 | G37: =D37+E37-F37 -> 73166.667 | H37: =H36+G37 -> 281500 | I37: =G37/(1+Inputs!B18)^($A37/12) -> 53575.188 | J37: =IF(H37>0,$A37,"") -> 33 | K37: =CHOOSE($B37+1,0,Inputs!C7,Inputs!C8,Inputs!C9) -> 0.9 | L37: =Inputs!C5*Inputs!C6*K37*Inputs!C10 -> 148500 | M37: =IF($B37=0,0,Inputs!C11*Inputs!C12*Inputs!C13/12*IF($B37=1,Inputs!C14,1)) -> 31250 | N37: =IF($A37<=Inputs!C16,Inputs!C15/Inputs!C16,Inputs!C17/12) -> 23333.333 | O37: =L37+M37-N37 -> 156416.67 | P37: =P36+O37 -> 2047750 | Q37: =O37/(1+Inputs!C18)^($A37/12) -> 114533.75 | R37: =IF(P37>0,$A37,"") -> 33
A38: 34 | B38: =IF(A38<=Inputs!$B$16,0,MIN(3,INT((A38-Inputs!$B$16-1)/12)+1)) -> 3 | C38: =CHOOSE($B38+1,0,Inputs!B7,Inputs!B8,Inputs!B9) -> 0.8 | D38: =Inputs!B5*Inputs!B6*C38*Inputs!B10 -> 84000 | E38: =IF($B38=0,0,Inputs!B11*Inputs!B12*Inputs!B13/12*IF($B38=1,Inputs!B14,1)) -> 12500 | F38: =IF($A38<=Inputs!B16,Inputs!B15/Inputs!B16,Inputs!B17/12) -> 23333.333 | G38: =D38+E38-F38 -> 73166.667 | H38: =H37+G38 -> 354666.67 | I38: =G38/(1+Inputs!B18)^($A38/12) -> 53071.603 | J38: =IF(H38>0,$A38,"") -> 34 | K38: =CHOOSE($B38+1,0,Inputs!C7,Inputs!C8,Inputs!C9) -> 0.9 | L38: =Inputs!C5*Inputs!C6*K38*Inputs!C10 -> 148500 | M38: =IF($B38=0,0,Inputs!C11*Inputs!C12*Inputs!C13/12*IF($B38=1,Inputs!C14,1)) -> 31250 | N38: =IF($A38<=Inputs!C16,Inputs!C15/Inputs!C16,Inputs!C17/12) -> 23333.333 | O38: =L38+M38-N38 -> 156416.67 | P38: =P37+O38 -> 2204166.7 | Q38: =O38/(1+Inputs!C18)^($A38/12) -> 113457.17 | R38: =IF(P38>0,$A38,"") -> 34
A39: 35 | B39: =IF(A39<=Inputs!$B$16,0,MIN(3,INT((A39-Inputs!$B$16-1)/12)+1)) -> 3 | C39: =CHOOSE($B39+1,0,Inputs!B7,Inputs!B8,Inputs!B9) -> 0.8 | D39: =Inputs!B5*Inputs!B6*C39*Inputs!B10 -> 84000 | E39: =IF($B39=0,0,Inputs!B11*Inputs!B12*Inputs!B13/12*IF($B39=1,Inputs!B14,1)) -> 12500 | F39: =IF($A39<=Inputs!B16,Inputs!B15/Inputs!B16,Inputs!B17/12) -> 23333.333 | G39: =D39+E39-F39 -> 73166.667 | H39: =H38+G39 -> 427833.33 | I39: =G39/(1+Inputs!B18)^($A39/12) -> 52572.751 | J39: =IF(H39>0,$A39,"") -> 35 | K39: =CHOOSE($B39+1,0,Inputs!C7,Inputs!C8,Inputs!C9) -> 0.9 | L39: =Inputs!C5*Inputs!C6*K39*Inputs!C10 -> 148500 | M39: =IF($B39=0,0,Inputs!C11*Inputs!C12*Inputs!C13/12*IF($B39=1,Inputs!C14,1)) -> 31250 | N39: =IF($A39<=Inputs!C16,Inputs!C15/Inputs!C16,Inputs!C17/12) -> 23333.333 | O39: =L39+M39-N39 -> 156416.67 | P39: =P38+O39 -> 2360583.3 | Q39: =O39/(1+Inputs!C18)^($A39/12) -> 112390.72 | R39: =IF(P39>0,$A39,"") -> 35
A40: 36 | B40: =IF(A40<=Inputs!$B$16,0,MIN(3,INT((A40-Inputs!$B$16-1)/12)+1)) -> 3 | C40: =CHOOSE($B40+1,0,Inputs!B7,Inputs!B8,Inputs!B9) -> 0.8 | D40: =Inputs!B5*Inputs!B6*C40*Inputs!B10 -> 84000 | E40: =IF($B40=0,0,Inputs!B11*Inputs!B12*Inputs!B13/12*IF($B40=1,Inputs!B14,1)) -> 12500 | F40: =IF($A40<=Inputs!B16,Inputs!B15/Inputs!B16,Inputs!B17/12) -> 23333.333 | G40: =D40+E40-F40 -> 73166.667 | H40: =H39+G40 -> 501000 | I40: =G40/(1+Inputs!B18)^($A40/12) -> 52078.588 | J40: =IF(H40>0,$A40,"") -> 36 | K40: =CHOOSE($B40+1,0,Inputs!C7,Inputs!C8,Inputs!C9) -> 0.9 | L40: =Inputs!C5*Inputs!C6*K40*Inputs!C10 -> 148500 | M40: =IF($B40=0,0,Inputs!C11*Inputs!C12*Inputs!C13/12*IF($B40=1,Inputs!C14,1)) -> 31250 | N40: =IF($A40<=Inputs!C16,Inputs!C15/Inputs!C16,Inputs!C17/12) -> 23333.333 | O40: =L40+M40-N40 -> 156416.67 | P40: =P39+O40 -> 2517000 | Q40: =O40/(1+Inputs!C18)^($A40/12) -> 111334.29 | R40: =IF(P40>0,$A40,"") -> 36

Sheet How it works
A1: How the model works
A2: Build: build cost is spread evenly over the build months. Benefits start the month after.
A3: Cost saved per month = volume x cost per unit x share AI-assisted x cost saved per unit. The share steps up each year after launch.
A4: Uplift per month = revenue x margin x uplift / 12. Year 1 after launch reaches only the share set in Inputs.
A5: Run cost is charged monthly from launch. NPV discounts each month at the annual rate. ROI = (benefit - cost) / cost.
A6: Breakeven is the first month in which cumulative net value is above zero. It uses undiscounted values.
A7: Defaults are the fictional retail example from the marketing page. Overwrite them with your own.
